LICENSE
MANIFEST.in
README.rst
setup.py
django_entity_subscription.egg-info/PKG-INFO
django_entity_subscription.egg-info/SOURCES.txt
django_entity_subscription.egg-info/dependency_links.txt
django_entity_subscription.egg-info/not-zip-safe
django_entity_subscription.egg-info/requires.txt
django_entity_subscription.egg-info/top_level.txt
entity_subscription/__init__.py
entity_subscription/admin.py
entity_subscription/models.py
entity_subscription/version.py
entity_subscription/migrations/0001_initial.py
entity_subscription/migrations/0002_auto__add_field_subscription_subentity_kind.py
entity_subscription/migrations/0003_auto__del_field_subscription_subentity_type.py
entity_subscription/migrations/__init__.py
entity_subscription/tests/__init__.py
entity_subscription/tests/admin_test.py
entity_subscription/tests/models_tests.py
entity_subscription/tests/tests.py