Metadata-Version: 1.1
Name: django-entity-subscription
Version: 0.4.1
Summary: Make subscription management easy and entity-based.
Home-page: https://github.com/ambitioninc/django-entity-subscription
Author: Erik Swanson
Author-email: opensource@ambition.com
License: MIT
Platform: UNKNOWN
Classifier: Programming Language :: Python
Classifier: Intended Audience :: Developers
Classifier: License :: OSI Approved :: MIT License
Classifier: Operating System :: OS Independent
Classifier: Framework :: Django
